extendjsonapi/__init__.py
extendjsonapi-0.1.0.dist-info/METADATA
extendjsonapi-0.1.0.dist-info/WHEEL
extendjsonapi-0.1.0.dist-info/RECORD
